mistfs_mcp_server-0.0.5.dist-info/licenses/LICENSE
mistfs_tools/__init__.py
mistfs_tools/__main__.py
mistfs_tools/server.py
mistfs_mcp_server-0.0.5.dist-info/METADATA
mistfs_mcp_server-0.0.5.dist-info/WHEEL
mistfs_mcp_server-0.0.5.dist-info/entry_points.txt
mistfs_mcp_server-0.0.5.dist-info/top_level.txt
mistfs_mcp_server-0.0.5.dist-info/RECORD
