Metadata-Version: 2.4
Name: mistfs-mcp-server
Version: 0.0.5
Summary: Model Context Protocol (MCP) server providing integrated tools for Microsoft Team Foundation Server (TFS) operations. Features include:
Author-email: swapnil dagade <swapnildagade@gmail.com>
License: MIT
Project-URL: Homepage, https://github.com/swapnildagade/mistfs-mcp-server
Project-URL: Bug Tracker, https://github.com/swapnildagade/mistfs-mcp-server/issues
Project-URL: Documentation, https://github.com/swapnildagade/mistfs-mcp-server#readme
Keywords: mcp,model-context-protocol,tfs,team-foundation-server,version-control,git,repository-management,commit-history,devops
Classifier: Programming Language :: Python :: 3
Classifier: License :: OSI Approved :: MIT License
Classifier: Operating System :: OS Independent
Classifier: Development Status :: 5 - Production/Stable
Classifier: Intended Audience :: Developers
Classifier: Topic :: Software Development :: Version Control
Classifier: Topic :: Software Development :: Libraries :: Python Modules
Classifier: Environment :: Win32 (MS Windows)
Classifier: Intended Audience :: Information Technology
Requires-Python: >=3.9
License-File: LICENSE
Requires-Dist: mcp>=1.2.0
Requires-Dist: requests
Requires-Dist: urllib3
Requires-Dist: logging
Dynamic: license-file
